LICENSE
MANIFEST.in
README.md
setup.cfg
setup.py
django_mp_tags.egg-info/PKG-INFO
django_mp_tags.egg-info/SOURCES.txt
django_mp_tags.egg-info/dependency_links.txt
django_mp_tags.egg-info/top_level.txt
tags/__init__.py
tags/actions.py
tags/admin.py
tags/forms.py
tags/models.py
tags/settings.py
tags/translation.py
tags/locale/ru/LC_MESSAGES/django.mo
tags/locale/ru/LC_MESSAGES/django.po
tags/locale/uk/LC_MESSAGES/django.mo
tags/locale/uk/LC_MESSAGES/django.po
tags/migrations/0001_initial.py
tags/migrations/0002_translation_fields.py
tags/migrations/__init__.py
tags/templates/tags/add_tag_groups_action.html