Metadata-Version: 2.1
Name: django-mp-tags
Version: 1.0.0
Summary: Django tags apps
Home-page: https://github.com/pmaigutyak/mp-tags
Download-URL: https://github.com/pmaigutyak/mp-tags/archive/1.0.0.tar.gz
Author: Paul Maigutyak
Author-email: pmaigutyak@gmail.com
License: MIT
License-File: LICENSE
